django_restup-0.1.1.dist-info/DESCRIPTION.rst
django_restup-0.1.1.dist-info/METADATA
django_restup-0.1.1.dist-info/RECORD
django_restup-0.1.1.dist-info/WHEEL
django_restup-0.1.1.dist-info/metadata.json
django_restup-0.1.1.dist-info/top_level.txt
restup/__init__.py
restup/constants.py
restup/exceptions.py
restup/resources.py
restup/serializers.py
restup/tests.py
restup/utils.py
restup/views.py
