Metadata-Version: 2.0
Name: django-restup
Version: 0.1.1
Summary: A Library for creating REST APIs for Django applications
Home-page: https://github.com/FFX01/django-restup
Author: Justin Walters
Author-email: walters.justin01@gmail.com
License: BSD
Keywords: django rest api
Platform: UNKNOWN
Classifier: Development Status :: 3 - Alpha
Classifier: Environment :: Web Environment
Classifier: Framework :: Django :: 1.10
Classifier: Intended Audience :: Developers
Classifier: License :: OSI Approved :: BSD License
Classifier: Natural Language :: English
Classifier: Operating System :: OS Independent
Classifier: Programming Language :: Python :: 3.4
Classifier: Programming Language :: Python :: 3.5
Classifier: Programming Language :: Python :: 3.6
Classifier: Programming Language :: Python :: 3 :: Only
Classifier: Programming Language :: Python :: Implementation :: CPython
Classifier: Topic :: Internet :: WWW/HTTP :: WSGI :: Application
Classifier: Topic :: Database :: Front-Ends
Requires-Dist: django (>=1.8)
